nx5d/__init__.py
nx5d/_version.py
nx5d/edf.py
nx5d/ingest.py
nx5d/nx.py
nx5d/recipe.py
nx5d/runlog.py
nx5d/scan.py
nx5d/slim.py
nx5d/spice.py
nx5d/streaks.py
nx5d/suitcase.py
nx5d/h5like/__init__.py
nx5d/h5like/fio.py
nx5d/h5like/h5pickle.py
nx5d/h5like/pypod.py
nx5d/h5like/spec.py
nx5d/h5like/tools.py
nx5d/h5like/xfel.py
nx5d/repo/__init__.py
nx5d/repo/astor.py
nx5d/repo/base.py
nx5d/repo/filesystem.py
nx5d/xrd/ColonelSandersFinest.py
nx5d/xrd/__init__.py
nx5d/xrd/analysis.py
nx5d/xrd/base.py
nx5d/xrd/esrf_id09.py
nx5d/xrd/experiment-xpp.yml
nx5d/xrd/experiment.py
nx5d/xrd/h5experiment.py
nx5d/xrd/kmc3.py
nx5d/xrd/petra3.py
nx5d/xrd/roi.py
nx5d/xrd/signal.py
nx5d/xrd/udkm.py
nx5d/xrd/xfel.py
nx5d/xrd/xraytest.py
nx5d/xrd/xrd_helpers.py
nx5d-2.0.1.dist-info/licenses/COPYING.md
nx5d-2.0.1.dist-info/METADATA
nx5d-2.0.1.dist-info/WHEEL
nx5d-2.0.1.dist-info/entry_points.txt
nx5d-2.0.1.dist-info/top_level.txt
nx5d-2.0.1.dist-info/RECORD
