Metadata-Version: 2.4
Name: nx5d
Version: 2.0.1
Summary: NX5 Duct Tape
Author-email: Matthias Rössle <matthias.roessle@helmholtz-berlin.de>, Florin Boariu <florin.pt@rootshell.ro>
Project-URL: Source Code, https://gitlab.com/codedump2/nx5d/
Project-URL: Bug Tracker, https://gitlab.com/codedump2/nx5d/-/issues
Project-URL: Documentation, https://nx5d.readthedocs.io/
Classifier: Programming Language :: Python :: 3
Classifier: Operating System :: POSIX :: Linux
Classifier: Development Status :: 2 - Pre-Alpha
Classifier: Environment :: Console
Classifier: Intended Audience :: Science/Research
Classifier: Topic :: Scientific/Engineering
Requires-Python: >=3.8
License-File: COPYING.md
Requires-Dist: numpy
Requires-Dist: h5py
Requires-Dist: xarray
Requires-Dist: silx
Requires-Dist: xarray
Requires-Dist: tifffile
Requires-Dist: pathlib
Requires-Dist: cachetools
Requires-Dist: scipy
Requires-Dist: dask
Requires-Dist: parse
Requires-Dist: camagick>=0.3
Requires-Dist: more_itertools
Requires-Dist: caproto
Provides-Extra: all
Requires-Dist: nx5d[doc,kmc3,scratch,test,xfel,xrd]; extra == "all"
Provides-Extra: test
Requires-Dist: pytest; extra == "test"
Requires-Dist: pytest-cov; extra == "test"
Requires-Dist: nx5d[doc,kmc3,scratch,xfel,xrd]; extra == "test"
Requires-Dist: tqdm; extra == "test"
Requires-Dist: schema; extra == "test"
Provides-Extra: doc
Requires-Dist: mkdocs; extra == "doc"
Requires-Dist: mkdocstrings[python]; extra == "doc"
Requires-Dist: mkdocs-jupyter; extra == "doc"
Provides-Extra: xrd
Requires-Dist: xrayutilities; extra == "xrd"
Provides-Extra: scratch
Requires-Dist: fabio; extra == "scratch"
Provides-Extra: xfel
Requires-Dist: extra_data; extra == "xfel"
Dynamic: license-file
